{
  "accentColor": "{{appsmith.theme.colors.primaryColor}}",
  "animateLoading": true,
  "borderRadius": "{{appsmith.theme.borderRadius.appBorderRadius}}",
  "bottomRow": 32,
  "boxShadow": "none",
  "defaultOptionValue": "",
  "dynamicBindingPathList": [
    {
      "key": "accentColor"
    },
    {
      "key": "borderRadius"
    },
    {
      "key": "sourceData"
    },
    {
      "key": "labelText"
    }
  ],
  "dynamicHeight": "FIXED",
  "dynamicPropertyPathList": [
    {
      "key": "sourceData"
    }
  ],
  "dynamicTriggerPathList": [],
  "isDisabled": false,
  "isFilterable": true,
  "isLoading": false,
  "isRequired": false,
  "isVisible": true,
  "key": "wotb8yl0c9",
  "labelAlignment": "left",
  "labelPosition": "Top",
  "labelText": "Server Current: {{\n  (\n    (get_domains.data?.data || [])\n      .find(d => String(d.id) === String(PatchDomain_Name.selectedOptionValue))\n      ?.server?.name\n    ?? \"NULL\"\n  ).toString()\n}}",
  "labelTextSize": "0.875rem",
  "labelWidth": 5,
  "leftColumn": 2,
  "maxDynamicHeight": 9000,
  "minDynamicHeight": 4,
  "minWidth": 450,
  "mobileBottomRow": 31,
  "mobileLeftColumn": 9,
  "mobileRightColumn": 29,
  "mobileTopRow": 24,
  "needsErrorInfo": false,
  "optionLabel": "label",
  "optionValue": "value",
  "originalBottomRow": 32,
  "originalTopRow": 25,
  "parentColumnSpace": 3.836669921875,
  "parentId": "jaif070irn",
  "parentRowSpace": 10,
  "placeholderText": "Select option",
  "renderMode": "CANVAS",
  "responsiveBehavior": "fill",
  "rightColumn": 56,
  "serverSideFiltering": false,
  "sourceData": "{{\n  (get_servers.data.data || []).map(s => ({\n    label: s.name || `Server #${s.id}`,\n    value: String(s.id)\n  }))\n}}",
  "topRow": 25,
  "type": "SELECT_WIDGET",
  "version": 1,
  "widgetId": "qyiavrcbu0",
  "widgetName": "PatchDomain_Server"
}